cfgtools/__init__.py
cfgtools/_typing.py
cfgtools/_version.py
cfgtools/basic.py
cfgtools/cli.py
cfgtools/core.py
cfgtools/css.py
cfgtools/iowrapper.py
cfgtools/reader.py
cfgtools/saver.py
cfgtools/templatelib.py
cfgtools/test_case.py
cfgtools-0.0.9.dist-info/METADATA
cfgtools-0.0.9.dist-info/WHEEL
cfgtools-0.0.9.dist-info/entry_points.txt
cfgtools-0.0.9.dist-info/licenses/LICENSE
cfgtools-0.0.9.dist-info/RECORD
