Metadata-Version: 2.4
Name: cfgtools
Version: 0.0.9
Summary: Provides tools for managing config files.
Project-URL: Documentation, https://github.com/Chitaoji/cfgtools/blob/main/README.md
Project-URL: Repository, https://github.com/Chitaoji/cfgtools/
Author-email: Chitaoji <2360742040@qq.com>
Maintainer-email: Chitaoji <2360742040@qq.com>
License-Expression: BSD-3-Clause
License-File: LICENSE
Keywords: config
Classifier: Programming Language :: Python :: 3
Classifier: Programming Language :: Python :: 3.12
Requires-Python: >=3.12
Requires-Dist: faker
Requires-Dist: htmlmaster
Requires-Dist: lazyr
Requires-Dist: pyyaml
Requires-Dist: toml
